xled_plus/__init__.py
xled_plus/colorcontrol.py
xled_plus/colormeander.py
xled_plus/discoverall.py
xled_plus/effect_base.py
xled_plus/effects.py
xled_plus/highcontrol.py
xled_plus/ledcolor.py
xled_plus/multicontrol.py
xled_plus/pattern.py
xled_plus/sequence.py
xled_plus/shapes.py
xled_plus/show_text.py
xled_plus/show_text2.py
xled_plus/xled_colorcontrol.py
xled_plus/xled_colorpicker.py
xled_plus/xled_picture.py
xled_plus/samples/candycane.py
xled_plus/samples/colmeander.py
xled_plus/samples/day1.py
xled_plus/samples/day10.py
xled_plus/samples/day11.py
xled_plus/samples/day12.py
xled_plus/samples/day13.py
xled_plus/samples/day14.py
xled_plus/samples/day15.py
xled_plus/samples/day16.py
xled_plus/samples/day17.py
xled_plus/samples/day18.py
xled_plus/samples/day19.py
xled_plus/samples/day2.py
xled_plus/samples/day20.py
xled_plus/samples/day21.py
xled_plus/samples/day22.py
xled_plus/samples/day23.py
xled_plus/samples/day24.py
xled_plus/samples/day25.py
xled_plus/samples/day26.py
xled_plus/samples/day27.py
xled_plus/samples/day28.py
xled_plus/samples/day29.py
xled_plus/samples/day3.py
xled_plus/samples/day30.py
xled_plus/samples/day31a.py
xled_plus/samples/day31b.py
xled_plus/samples/day4.py
xled_plus/samples/day5.py
xled_plus/samples/day6.py
xled_plus/samples/day7.py
xled_plus/samples/day8.py
xled_plus/samples/day9.py
xled_plus/samples/sample_setup.py
xled_plus/samples/sample_setup_new.py
xled_plus/samples/spectrum.py
xled_plus/samples/spectrumlight.py
xled_plus-0.1.37.dist-info/LICENSE
xled_plus-0.1.37.dist-info/METADATA
xled_plus-0.1.37.dist-info/WHEEL
xled_plus-0.1.37.dist-info/top_level.txt
xled_plus-0.1.37.dist-info/RECORD
